oc_declare-0.1.1.dist-info/METADATA
oc_declare-0.1.1.dist-info/WHEEL
oc_declare/__init__.py
oc_declare/__init__.pyi
oc_declare/oc_declare.cp313-win_amd64.pyd
oc_declare/py.typed
oc_declare-0.1.1.dist-info/RECORD
