Metadata-Version: 2.4
Name: oc_declare
Version: 0.1.1
Classifier: Programming Language :: Rust
Classifier: Programming Language :: Python :: Implementation :: CPython
Classifier: Programming Language :: Python :: Implementation :: PyPy
Summary: Python Bindings for OC-DECLARE: Discovering Object-Centric Declarative Patterns with Synchronization
Keywords: process-mining,process,mining,OC-DECLARE,object-centric,DECLARE
Author-email: Aaron Küsters <kuesters@pads.rwth-aachen.de>
Requires-Python: >=3.8
